Asynchronous/dff.sv
module dff(output reg q, input wire clk, reset, d);

    always @(posedge clk) 
    begin
        if (reset)
            q <= 1'b0;   
        else
            q <= d;  
    end

endmodule

Synchronous/xorgate.sv
module xorgate(input a, b, output o);

assign o = a ^ b;

endmodule

Synchronous/andgate.sv
module andgate(input a, b, output o);

assign o = a & b;

endmodule

Synchronous/evencounter.sv
module evencounter (input wire clk, reset, output [7:0]q);
    wire d2, d3, d4, d5, d6, d7, y3, y4, y5, y6, y7;
    dff D0 (q[0], clk, reset, q[0]);
    dff D1 (q[1], clk, reset, ~q[1]);
    xorgate x2 (q[1], q[2], d2);
    dff D2 (q[2], clk, reset, d2);
    andgate a3 (q[1], q[2], y3);
    xorgate x3 (y3, q[3], d3);
    dff D3 (q[3], clk, reset, d3);
    andgate a4 (y3, q[3], y4);
    xorgate x4 (y4, q[4], d4);
    dff D4 (q[4], clk, reset, d4);
    andgate a5 (y4, q[4], y5);
    xorgate x5 (y5, q[5], d5);
    dff D5 (q[5], clk, reset, d5);
    andgate a6 (y5, q[5], y6);
    xorgate x6 (y6, q[6], d6);
    dff D6 (q[6], clk, reset, d6);
    andgate a7 (y6, q[6], y7);
    xorgate x7 (y7, q[7], d7);
    dff D7 (q[7], clk, reset, d7);
endmodule

Synchronous/testbench.sv
module testbench;

    import counter_pkg::*;
    EightBitEvenUpCounter E;
    reg clk, reset;
    wire [7:0]q;//expected even counter value
    logic [7:0]temp = 8'b0;

    evencounter dut(.clk(clk),.reset(reset),.q(q));
    
    always #1 clk = ~clk;

    initial begin  
        $dumpfile("testbench.vcd");
        $dumpvars(0,testbench); 
        clk <= 1'b0;
        reset = 1'b1;
        #5 reset = ~reset;
        repeat(128) begin            
            varify(clk, reset);                   
            #2 $display("expected = %d, got = %d", E.count, q);                
        end
        $finish;
    end

    task varify;
        input clk, reset;
        begin
            E = new(clk, reset);
            E.getvalue(temp);//value of temp goes to package
            temp = E.count;
        end
    endtask

endmodule

Synchronous/testbench.vcd
$date
	Tue Aug 08 18:04:08 2023
$end
$version
	Icarus Verilog
$end
$timescale
	1s
$end
$scope module testbench $end
$var wire 8 ! q [7:0] $end
$var reg 1 " clk $end
$var reg 1 # reset $end
$var reg 8 $ temp [7:0] $end
$scope module dut $end
$var wire 1 " clk $end
$var wire 1 # reset $end
$var wire 1 % y7 $end
$var wire 1 & y6 $end
$var wire 1 ' y5 $end
$var wire 1 ( y4 $end
$var wire 1 ) y3 $end
$var wire 8 * q [7:0] $end
$var wire 1 + d7 $end
$var wire 1 , d6 $end
$var wire 1 - d5 $end
$var wire 1 . d4 $end
$var wire 1 / d3 $end
$var wire 1 0 d2 $end
$scope module D0 $end
$var wire 1 " clk $end
$var wire 1 1 d $end
$var wire 1 # reset $end
$var reg 1 2 q $end
$upscope $end
$scope module D1 $end
$var wire 1 " clk $end
$var wire 1 3 d $end
$var wire 1 # reset $end
$var reg 1 4 q $end
$upscope $end
$scope module D2 $end
$var wire 1 " clk $end
$var wire 1 # reset $end
$var wire 1 0 d $end
$var reg 1 5 q $end
$upscope $end
$scope module D3 $end
$var wire 1 " clk $end
$var wire 1 # reset $end
$var wire 1 / d $end
$var reg 1 6 q $end
$upscope $end
$scope module D4 $end
$var wire 1 " clk $end
$var wire 1 # reset $end
$var wire 1 . d $end
$var reg 1 7 q $end
$upscope $end
$scope module D5 $end
$var wire 1 " clk $end
$var wire 1 # reset $end
$var wire 1 - d $end
$var reg 1 8 q $end
$upscope $end
$scope module D6 $end
$var wire 1 " clk $end
$var wire 1 # reset $end
$var wire 1 , d $end
$var reg 1 9 q $end
$upscope $end
$scope module D7 $end
$var wire 1 " clk $end
$var wire 1 # reset $end
$var wire 1 + d $end
$var reg 1 : q $end
$upscope $end
$scope module a3 $end
$var wire 1 ; a $end
$var wire 1 < b $end
$var wire 1 ) o $end
$upscope $end
$scope module a4 $end
$var wire 1 ) a $end
$var wire 1 = b $end
$var wire 1 ( o $end
$upscope $end
$scope module a5 $end
$var wire 1 ( a $end
$var wire 1 > b $end
$var wire 1 ' o $end
$upscope $end
$scope module a6 $end
$var wire 1 ' a $end
$var wire 1 ? b $end
$var wire 1 & o $end
$upscope $end
$scope module a7 $end
$var wire 1 & a $end
$var wire 1 @ b $end
$var wire 1 % o $end
$upscope $end
$scope module x2 $end
$var wire 1 A a $end
$var wire 1 B b $end
$var wire 1 0 o $end
$upscope $end
$scope module x3 $end
$var wire 1 ) a $end
$var wire 1 C b $end
$var wire 1 / o $end
$upscope $end
$scope module x4 $end
$var wire 1 ( a $end
$var wire 1 D b $end
$var wire 1 . o $end
$upscope $end
$scope module x5 $end
$var wire 1 ' a $end
$var wire 1 E b $end
$var wire 1 - o $end
$upscope $end
$scope module x6 $end
$var wire 1 & a $end
$var wire 1 F b $end
$var wire 1 , o $end
$upscope $end
$scope module x7 $end
$var wire 1 % a $end
$var wire 1 G b $end
$var wire 1 + o $end
$upscope $end
$upscope $end
$scope task varify $end
$var reg 1 H clk $end
$var reg 1 I reset $end
$upscope $end
$upscope $end
$enddefinitions $end
$comment Show the parameter values. $end
$dumpall
$end
#0
$dumpvars
xI
xH
xG
xF
xE
xD
xC
xB
xA
x@
x?
x>
x=
x<
x;
x:
x9
x8
x7
x6
x5
x4
x3
x2
x1
x0
x/
x.
x-
x,
x+
bx *
x)
x(
x'
x&
x%
b0 $
1#
0"
bx !
$end
#1
0/
0.
0-
0,
0+
13
0)
00
0(
0'
0&
0%
01
0;
0A
0<
0B
0=
0C
0>
0D
0?
0E
0@
0F
0G
02
04
05
06
07
08
09
b0 !
b0 *
0:
1"
#2
0"
#3
1"
#4
0"
#5
10
03
1;
1A
b10 !
b10 *
14
1"
b10 $
0I
0H
0#
#6
0"
#7
13
1<
1B
0;
0A
15
b100 !
b100 *
04
1"
b100 $
#8
0"
#9
1/
1)
00
03
1;
1A
b110 !
b110 *
14
1"
b110 $
#10
0"
#11
0)
13
1=
1C
0<
0B
0;
0A
16
05
b1000 !
b1000 *
04
1"
b1000 $
#12
0"
#13
10
03
1;
1A
b1010 !
b1010 *
14
1"
b1010 $
#14
0"
#15
13
1<
1B
0;
0A
15
b1100 !
b1100 *
04
1"
b1100 $
#16
0"
#17
1.
1(
0/
1)
00
03
1;
1A
b1110 !
b1110 *
14
1"
b1110 $
#18
0"
#19
0(
0)
13
1>
1D
0=
0C
0<
0B
0;
0A
17
06
05
b10000 !
b10000 *
04
1"
b10000 $
#20
0"
#21
10
03
1;
1A
b10010 !
b10010 *
14
1"
b10010 $
#22
0"
#23
13
1<
1B
0;
0A
15
b10100 !
b10100 *
04
1"
b10100 $
#24
0"
#25
1/
1)
00
03
1;
1A
b10110 !
b10110 *
14
1"
b10110 $
#26
0"
#27
0)
13
1=
1C
0<
0B
0;
0A
16
05
b11000 !
b11000 *
04
1"
b11000 $
#28
0"
#29
10
03
1;
1A
b11010 !
b11010 *
14
1"
b11010 $
#30
0"
#31
13
1<
1B
0;
0A
15
b11100 !
b11100 *
04
1"
b11100 $
#32
0"
#33
1-
1'
0.
1(
0/
1)
00
03
1;
1A
b11110 !
b11110 *
14
1"
b11110 $
#34
0"
#35
0'
0(
0)
13
1?
1E
0>
0D
0=
0C
0<
0B
0;
0A
18
07
06
05
b100000 !
b100000 *
04
1"
b100000 $
#36
0"
#37
10
03
1;
1A
b100010 !
b100010 *
14
1"
b100010 $
#38
0"
#39
13
1<
1B
0;
0A
15
b100100 !
b100100 *
04
1"
b100100 $
#40
0"
#41
1/
1)
00
03
1;
1A
b100110 !
b100110 *
14
1"
b100110 $
#42
0"
#43
0)
13
1=
1C
0<
0B
0;
0A
16
05
b101000 !
b101000 *
04
1"
b101000 $
#44
0"
#45
10
03
1;
1A
b101010 !
b101010 *
14
1"
b101010 $
#46
0"
#47
13
1<
1B
0;
0A
15
b101100 !
b101100 *
04
1"
b101100 $
#48
0"
#49
1.
1(
0/
1)
00
03
1;
1A
b101110 !
b101110 *
14
1"
b101110 $
#50
0"
#51
0(
0)
13
1>
1D
0=
0C
0<
0B
0;
0A
17
06
05
b110000 !
b110000 *
04
1"
b110000 $
#52
0"
#53
10
03
1;
1A
b110010 !
b110010 *
14
1"
b110010 $
#54
0"
#55
13
1<
1B
0;
0A
15
b110100 !
b110100 *
04
1"
b110100 $
#56
0"
#57
1/
1)
00
03
1;
1A
b110110 !
b110110 *
14
1"
b110110 $
#58
0"
#59
0)
13
1=
1C
0<
0B
0;
0A
16
05
b111000 !
b111000 *
04
1"
b111000 $
#60
0"
#61
10
03
1;
1A
b111010 !
b111010 *
14
1"
b111010 $
#62
0"
#63
13
1<
1B
0;
0A
15
b111100 !
b111100 *
04
1"
b111100 $
#64
0"
#65
1,
1&
0-
1'
0.
1(
0/
1)
00
03
1;
1A
b111110 !
b111110 *
14
1"
b111110 $
#66
0"
#67
0&
0'
0(
0)
13
1@
1F
0?
0E
0>
0D
0=
0C
0<
0B
0;
0A
19
08
07
06
05
b1000000 !
b1000000 *
04
1"
b1000000 $
#68
0"
#69
10
03
1;
1A
b1000010 !
b1000010 *
14
1"
b1000010 $
#70
0"
#71
13
1<
1B
0;
0A
15
b1000100 !
b1000100 *
04
1"
b1000100 $
#72
0"
#73
1/
1)
00
03
1;
1A
b1000110 !
b1000110 *
14
1"
b1000110 $
#74
0"
#75
0)
13
1=
1C
0<
0B
0;
0A
16
05
b1001000 !
b1001000 *
04
1"
b1001000 $
#76
0"
#77
10
03
1;
1A
b1001010 !
b1001010 *
14
1"
b1001010 $
#78
0"
#79
13
1<
1B
0;
0A
15
b1001100 !
b1001100 *
04
1"
b1001100 $
#80
0"
#81
1.
1(
0/
1)
00
03
1;
1A
b1001110 !
b1001110 *
14
1"
b1001110 $
#82
0"
#83
0(
0)
13
1>
1D
0=
0C
0<
0B
0;
0A
17
06
05
b1010000 !
b1010000 *
04
1"
b1010000 $
#84
0"
#85
10
03
1;
1A
b1010010 !
b1010010 *
14
1"
b1010010 $
#86
0"
#87
13
1<
1B
0;
0A
15
b1010100 !
b1010100 *
04
1"
b1010100 $
#88
0"
#89
1/
1)
00
03
1;
1A
b1010110 !
b1010110 *
14
1"
b1010110 $
#90
0"
#91
0)
13
1=
1C
0<
0B
0;
0A
16
05
b1011000 !
b1011000 *
04
1"
b1011000 $
#92
0"
#93
10
03
1;
1A
b1011010 !
b1011010 *
14
1"
b1011010 $
#94
0"
#95
13
1<
1B
0;
0A
15
b1011100 !
b1011100 *
04
1"
b1011100 $
#96
0"
#97
1-
1'
0.
1(
0/
1)
00
03
1;
1A
b1011110 !
b1011110 *
14
1"
b1011110 $
#98
0"
#99
0'
0(
0)
13
1?
1E
0>
0D
0=
0C
0<
0B
0;
0A
18
07
06
05
b1100000 !
b1100000 *
04
1"
b1100000 $
#100
0"
#101
10
03
1;
1A
b1100010 !
b1100010 *
14
1"
b1100010 $
#102
0"
#103
13
1<
1B
0;
0A
15
b1100100 !
b1100100 *
04
1"
b1100100 $
#104
0"
#105
1/
1)
00
03
1;
1A
b1100110 !
b1100110 *
14
1"
b1100110 $
#106
0"
#107
0)
13
1=
1C
0<
0B
0;
0A
16
05
b1101000 !
b1101000 *
04
1"
b1101000 $
#108
0"
#109
10
03
1;
1A
b1101010 !
b1101010 *
14
1"
b1101010 $
#110
0"
#111
13
1<
1B
0;
0A
15
b1101100 !
b1101100 *
04
1"
b1101100 $
#112
0"
#113
1.
1(
0/
1)
00
03
1;
1A
b1101110 !
b1101110 *
14
1"
b1101110 $
#114
0"
#115
0(
0)
13
1>
1D
0=
0C
0<
0B
0;
0A
17
06
05
b1110000 !
b1110000 *
04
1"
b1110000 $
#116
0"
#117
10
03
1;
1A
b1110010 !
b1110010 *
14
1"
b1110010 $
#118
0"
#119
13
1<
1B
0;
0A
15
b1110100 !
b1110100 *
04
1"
b1110100 $
#120
0"
#121
1/
1)
00
03
1;
1A
b1110110 !
b1110110 *
14
1"
b1110110 $
#122
0"
#123
0)
13
1=
1C
0<
0B
0;
0A
16
05
b1111000 !
b1111000 *
04
1"
b1111000 $
#124
0"
#125
10
03
1;
1A
b1111010 !
b1111010 *
14
1"
b1111010 $
#126
0"
#127
13
1<
1B
0;
0A
15
b1111100 !
b1111100 *
04
1"
b1111100 $
#128
0"
#129
1+
1%
0,
1&
0-
1'
0.
1(
0/
1)
00
03
1;
1A
b1111110 !
b1111110 *
14
1"
b1111110 $
#130
0"
#131
0%
0&
0'
0(
0)
13
1G
0@
0F
0?
0E
0>
0D
0=
0C
0<
0B
0;
0A
1:
09
08
07
06
05
b10000000 !
b10000000 *
04
1"
b10000000 $
#132
0"
#133
10
03
1;
1A
b10000010 !
b10000010 *
14
1"
b10000010 $
#134
0"
#135
13
1<
1B
0;
0A
15
b10000100 !
b10000100 *
04
1"
b10000100 $
#136
0"
#137
1/
1)
00
03
1;
1A
b10000110 !
b10000110 *
14
1"
b10000110 $
#138
0"
#139
0)
13
1=
1C
0<
0B
0;
0A
16
05
b10001000 !
b10001000 *
04
1"
b10001000 $
#140
0"
#141
10
03
1;
1A
b10001010 !
b10001010 *
14
1"
b10001010 $
#142
0"
#143
13
1<
1B
0;
0A
15
b10001100 !
b10001100 *
04
1"
b10001100 $
#144
0"
#145
1.
1(
0/
1)
00
03
1;
1A
b10001110 !
b10001110 *
14
1"
b10001110 $
#146
0"
#147
0(
0)
13
1>
1D
0=
0C
0<
0B
0;
0A
17
06
05
b10010000 !
b10010000 *
04
1"
b10010000 $
#148
0"
#149
10
03
1;
1A
b10010010 !
b10010010 *
14
1"
b10010010 $
#150
0"
#151
13
1<
1B
0;
0A
15
b10010100 !
b10010100 *
04
1"
b10010100 $
#152
0"
#153
1/
1)
00
03
1;
1A
b10010110 !
b10010110 *
14
1"
b10010110 $
#154
0"
#155
0)
13
1=
1C
0<
0B
0;
0A
16
05
b10011000 !
b10011000 *
04
1"
b10011000 $
#156
0"
#157
10
03
1;
1A
b10011010 !
b10011010 *
14
1"
b10011010 $
#158
0"
#159
13
1<
1B
0;
0A
15
b10011100 !
b10011100 *
04
1"
b10011100 $
#160
0"
#161
1-
1'
0.
1(
0/
1)
00
03
1;
1A
b10011110 !
b10011110 *
14
1"
b10011110 $
#162
0"
#163
0'
0(
0)
13
1?
1E
0>
0D
0=
0C
0<
0B
0;
0A
18
07
06
05
b10100000 !
b10100000 *
04
1"
b10100000 $
#164
0"
#165
10
03
1;
1A
b10100010 !
b10100010 *
14
1"
b10100010 $
#166
0"
#167
13
1<
1B
0;
0A
15
b10100100 !
b10100100 *
04
1"
b10100100 $
#168
0"
#169
1/
1)
00
03
1;
1A
b10100110 !
b10100110 *
14
1"
b10100110 $
#170
0"
#171
0)
13
1=
1C
0<
0B
0;
0A
16
05
b10101000 !
b10101000 *
04
1"
b10101000 $
#172
0"
#173
10
03
1;
1A
b10101010 !
b10101010 *
14
1"
b10101010 $
#174
0"
#175
13
1<
1B
0;
0A
15
b10101100 !
b10101100 *
04
1"
b10101100 $
#176
0"
#177
1.
1(
0/
1)
00
03
1;
1A
b10101110 !
b10101110 *
14
1"
b10101110 $
#178
0"
#179
0(
0)
13
1>
1D
0=
0C
0<
0B
0;
0A
17
06
05
b10110000 !
b10110000 *
04
1"
b10110000 $
#180
0"
#181
10
03
1;
1A
b10110010 !
b10110010 *
14
1"
b10110010 $
#182
0"
#183
13
1<
1B
0;
0A
15
b10110100 !
b10110100 *
04
1"
b10110100 $
#184
0"
#185
1/
1)
00
03
1;
1A
b10110110 !
b10110110 *
14
1"
b10110110 $
#186
0"
#187
0)
13
1=
1C
0<
0B
0;
0A
16
05
b10111000 !
b10111000 *
04
1"
b10111000 $
#188
0"
#189
10
03
1;
1A
b10111010 !
b10111010 *
14
1"
b10111010 $
#190
0"
#191
13
1<
1B
0;
0A
15
b10111100 !
b10111100 *
04
1"
b10111100 $
#192
0"
#193
1,
1&
0-
1'
0.
1(
0/
1)
00
03
1;
1A
b10111110 !
b10111110 *
14
1"
b10111110 $
#194
0"
#195
0&
0'
0(
0)
13
1@
1F
0?
0E
0>
0D
0=
0C
0<
0B
0;
0A
19
08
07
06
05
b11000000 !
b11000000 *
04
1"
b11000000 $
#196
0"
#197
10
03
1;
1A
b11000010 !
b11000010 *
14
1"
b11000010 $
#198
0"
#199
13
1<
1B
0;
0A
15
b11000100 !
b11000100 *
04
1"
b11000100 $
#200
0"
#201
1/
1)
00
03
1;
1A
b11000110 !
b11000110 *
14
1"
b11000110 $
#202
0"
#203
0)
13
1=
1C
0<
0B
0;
0A
16
05
b11001000 !
b11001000 *
04
1"
b11001000 $
#204
0"
#205
10
03
1;
1A
b11001010 !
b11001010 *
14
1"
b11001010 $
#206
0"
#207
13
1<
1B
0;
0A
15
b11001100 !
b11001100 *
04
1"
b11001100 $
#208
0"
#209
1.
1(
0/
1)
00
03
1;
1A
b11001110 !
b11001110 *
14
1"
b11001110 $
#210
0"
#211
0(
0)
13
1>
1D
0=
0C
0<
0B
0;
0A
17
06
05
b11010000 !
b11010000 *
04
1"
b11010000 $
#212
0"
#213
10
03
1;
1A
b11010010 !
b11010010 *
14
1"
b11010010 $
#214
0"
#215
13
1<
1B
0;
0A
15
b11010100 !
b11010100 *
04
1"
b11010100 $
#216
0"
#217
1/
1)
00
03
1;
1A
b11010110 !
b11010110 *
14
1"
b11010110 $
#218
0"
#219
0)
13
1=
1C
0<
0B
0;
0A
16
05
b11011000 !
b11011000 *
04
1"
b11011000 $
#220
0"
#221
10
03
1;
1A
b11011010 !
b11011010 *
14
1"
b11011010 $
#222
0"
#223
13
1<
1B
0;
0A
15
b11011100 !
b11011100 *
04
1"
b11011100 $
#224
0"
#225
1-
1'
0.
1(
0/
1)
00
03
1;
1A
b11011110 !
b11011110 *
14
1"
b11011110 $
#226
0"
#227
0'
0(
0)
13
1?
1E
0>
0D
0=
0C
0<
0B
0;
0A
18
07
06
05
b11100000 !
b11100000 *
04
1"
b11100000 $
#228
0"
#229
10
03
1;
1A
b11100010 !
b11100010 *
14
1"
b11100010 $
#230
0"
#231
13
1<
1B
0;
0A
15
b11100100 !
b11100100 *
04
1"
b11100100 $
#232
0"
#233
1/
1)
00
03
1;
1A
b11100110 !
b11100110 *
14
1"
b11100110 $
#234
0"
#235
0)
13
1=
1C
0<
0B
0;
0A
16
05
b11101000 !
b11101000 *
04
1"
b11101000 $
#236
0"
#237
10
03
1;
1A
b11101010 !
b11101010 *
14
1"
b11101010 $
#238
0"
#239
13
1<
1B
0;
0A
15
b11101100 !
b11101100 *
04
1"
b11101100 $
#240
0"
#241
1.
1(
0/
1)
00
03
1;
1A
b11101110 !
b11101110 *
14
1"
b11101110 $
#242
0"
#243
0(
0)
13
1>
1D
0=
0C
0<
0B
0;
0A
17
06
05
b11110000 !
b11110000 *
04
1"
b11110000 $
#244
0"
#245
10
03
1;
1A
b11110010 !
b11110010 *
14
1"
b11110010 $
#246
0"
#247
13
1<
1B
0;
0A
15
b11110100 !
b11110100 *
04
1"
b11110100 $
#248
0"
#249
1/
1)
00
03
1;
1A
b11110110 !
b11110110 *
14
1"
b11110110 $
#250
0"
#251
0)
13
1=
1C
0<
0B
0;
0A
16
05
b11111000 !
b11111000 *
04
1"
b11111000 $
#252
0"
#253
10
03
1;
1A
b11111010 !
b11111010 *
14
1"
b11111010 $
#254
0"
#255
13
1<
1B
0;
0A
15
b11111100 !
b11111100 *
04
1"
b11111100 $
#256
0"
#257
0+
1%
0,
1&
0-
1'
0.
1(
0/
1)
00
03
1;
1A
b11111110 !
b11111110 *
14
1"
b11111110 $
#258
0"
#259
0%
0&
0'
0(
0)
13
0G
0@
0F
0?
0E
0>
0D
0=
0C
0<
0B
0;
0A
0:
09
08
07
06
05
b0 !
b0 *
04
1"
b0 $
#260
0"
#261
10
03
1;
1A
b10 !
b10 *
14
1"
