Asynchronous/dff.sv
module dff(output reg q, input wire clk, reset, d);

    always @(posedge clk) 
    begin
        if (reset)
            q <= 1'b0;   
        else
            q <= d;  
    end

endmodule

Asynchronous/evencounter.sv
module evencount( input wire clk, reset, output [7:0]q);

    dff D0 (q[0], clk, reset, q[0]);
    dff D1 (q[1], clk, reset, ~q[1]);
    dff D2 (q[2], ~q[1], reset, ~q[2]);
    dff D3 (q[3], ~q[2], reset, ~q[3]);
    dff D4 (q[4], ~q[3], reset, ~q[4]);
    dff D5 (q[5], ~q[4], reset, ~q[5]);
    dff D6 (q[6], ~q[5], reset, ~q[6]);
    dff D7 (q[7], ~q[6], reset, ~q[7]);

endmodule

Asynchronous/testbench.sv
module testbench;

    import counter_pkg::*;
    EightBitEvenUpCounter E;
    reg clk, reset;
    wire [7:0]q;//expected even counter value
    logic [7:0]temp=8'b0;

    evencount dut(.clk(clk),.reset(reset),.q(q));

    always #1 clk = ~clk;

    initial begin   
        $dumpfile("testbench.vcd");
        $dumpvars(0,testbench); 
        clk <= 1'b0;
        reset = 1'b1;
        #5 reset = ~reset;     
        repeat(128) begin            
            varify(clk, reset);                   
            #2 $display("expected = %d, got = %d", E.count, q);                
        end
        $finish;
    end

    task varify;
        input clk, reset;
        begin
            E = new(clk, reset);
            E.getvalue(temp);//value of temp goes to package
            temp = E.count;
        end
    endtask

endmodule

Asynchronous/testbench.vcd
$date
	Tue Aug 08 18:03:27 2023
$end
$version
	Icarus Verilog
$end
$timescale
	1s
$end
$scope module testbench $end
$var wire 8 ! q [7:0] $end
$var reg 1 " clk $end
$var reg 1 # reset $end
$var reg 8 $ temp [7:0] $end
$scope module dut $end
$var wire 1 " clk $end
$var wire 1 # reset $end
$var wire 8 % q [7:0] $end
$scope module D0 $end
$var wire 1 " clk $end
$var wire 1 & d $end
$var wire 1 # reset $end
$var reg 1 ' q $end
$upscope $end
$scope module D1 $end
$var wire 1 " clk $end
$var wire 1 ( d $end
$var wire 1 # reset $end
$var reg 1 ) q $end
$upscope $end
$scope module D2 $end
$var wire 1 * clk $end
$var wire 1 + d $end
$var wire 1 # reset $end
$var reg 1 , q $end
$upscope $end
$scope module D3 $end
$var wire 1 - clk $end
$var wire 1 . d $end
$var wire 1 # reset $end
$var reg 1 / q $end
$upscope $end
$scope module D4 $end
$var wire 1 0 clk $end
$var wire 1 1 d $end
$var wire 1 # reset $end
$var reg 1 2 q $end
$upscope $end
$scope module D5 $end
$var wire 1 3 clk $end
$var wire 1 4 d $end
$var wire 1 # reset $end
$var reg 1 5 q $end
$upscope $end
$scope module D6 $end
$var wire 1 6 clk $end
$var wire 1 7 d $end
$var wire 1 # reset $end
$var reg 1 8 q $end
$upscope $end
$scope module D7 $end
$var wire 1 9 clk $end
$var wire 1 : d $end
$var wire 1 # reset $end
$var reg 1 ; q $end
$upscope $end
$upscope $end
$scope task varify $end
$var reg 1 < clk $end
$var reg 1 = reset $end
$upscope $end
$upscope $end
$enddefinitions $end
$comment Show the parameter values. $end
$dumpall
$end
#0
$dumpvars
x=
x<
x;
x:
x9
x8
x7
x6
x5
x4
x3
x2
x1
x0
x/
x.
x-
x,
x+
x*
x)
x(
x'
x&
bx %
b0 $
1#
0"
bx !
$end
#1
1:
0;
19
17
08
16
14
05
13
11
02
10
1.
0/
1-
1+
0,
1*
1(
0&
0'
b0 !
b0 %
0)
1"
#2
0"
#3
1"
#4
0"
#5
0*
0(
b10 !
b10 %
1)
1"
b10 $
0=
0<
0#
#6
0"
#7
0-
0+
1,
1*
1(
b100 !
b100 %
0)
1"
b100 $
#8
0"
#9
0*
0(
b110 !
b110 %
1)
1"
b110 $
#10
0"
#11
00
0.
1/
1-
1+
0,
1*
1(
b1000 !
b1000 %
0)
1"
b1000 $
#12
0"
#13
0*
0(
b1010 !
b1010 %
1)
1"
b1010 $
#14
0"
#15
0-
0+
1,
1*
1(
b1100 !
b1100 %
0)
1"
b1100 $
#16
0"
#17
0*
0(
b1110 !
b1110 %
1)
1"
b1110 $
#18
0"
#19
03
01
12
10
1.
0/
1-
1+
0,
1*
1(
b10000 !
b10000 %
0)
1"
b10000 $
#20
0"
#21
0*
0(
b10010 !
b10010 %
1)
1"
b10010 $
#22
0"
#23
0-
0+
1,
1*
1(
b10100 !
b10100 %
0)
1"
b10100 $
#24
0"
#25
0*
0(
b10110 !
b10110 %
1)
1"
b10110 $
#26
0"
#27
00
0.
1/
1-
1+
0,
1*
1(
b11000 !
b11000 %
0)
1"
b11000 $
#28
0"
#29
0*
0(
b11010 !
b11010 %
1)
1"
b11010 $
#30
0"
#31
0-
0+
1,
1*
1(
b11100 !
b11100 %
0)
1"
b11100 $
#32
0"
#33
0*
0(
b11110 !
b11110 %
1)
1"
b11110 $
#34
0"
#35
06
04
15
13
11
02
10
1.
0/
1-
1+
0,
1*
1(
b100000 !
b100000 %
0)
1"
b100000 $
#36
0"
#37
0*
0(
b100010 !
b100010 %
1)
1"
b100010 $
#38
0"
#39
0-
0+
1,
1*
1(
b100100 !
b100100 %
0)
1"
b100100 $
#40
0"
#41
0*
0(
b100110 !
b100110 %
1)
1"
b100110 $
#42
0"
#43
00
0.
1/
1-
1+
0,
1*
1(
b101000 !
b101000 %
0)
1"
b101000 $
#44
0"
#45
0*
0(
b101010 !
b101010 %
1)
1"
b101010 $
#46
0"
#47
0-
0+
1,
1*
1(
b101100 !
b101100 %
0)
1"
b101100 $
#48
0"
#49
0*
0(
b101110 !
b101110 %
1)
1"
b101110 $
#50
0"
#51
03
01
12
10
1.
0/
1-
1+
0,
1*
1(
b110000 !
b110000 %
0)
1"
b110000 $
#52
0"
#53
0*
0(
b110010 !
b110010 %
1)
1"
b110010 $
#54
0"
#55
0-
0+
1,
1*
1(
b110100 !
b110100 %
0)
1"
b110100 $
#56
0"
#57
0*
0(
b110110 !
b110110 %
1)
1"
b110110 $
#58
0"
#59
00
0.
1/
1-
1+
0,
1*
1(
b111000 !
b111000 %
0)
1"
b111000 $
#60
0"
#61
0*
0(
b111010 !
b111010 %
1)
1"
b111010 $
#62
0"
#63
0-
0+
1,
1*
1(
b111100 !
b111100 %
0)
1"
b111100 $
#64
0"
#65
0*
0(
b111110 !
b111110 %
1)
1"
b111110 $
#66
0"
#67
09
07
18
16
14
05
13
11
02
10
1.
0/
1-
1+
0,
1*
1(
b1000000 !
b1000000 %
0)
1"
b1000000 $
#68
0"
#69
0*
0(
b1000010 !
b1000010 %
1)
1"
b1000010 $
#70
0"
#71
0-
0+
1,
1*
1(
b1000100 !
b1000100 %
0)
1"
b1000100 $
#72
0"
#73
0*
0(
b1000110 !
b1000110 %
1)
1"
b1000110 $
#74
0"
#75
00
0.
1/
1-
1+
0,
1*
1(
b1001000 !
b1001000 %
0)
1"
b1001000 $
#76
0"
#77
0*
0(
b1001010 !
b1001010 %
1)
1"
b1001010 $
#78
0"
#79
0-
0+
1,
1*
1(
b1001100 !
b1001100 %
0)
1"
b1001100 $
#80
0"
#81
0*
0(
b1001110 !
b1001110 %
1)
1"
b1001110 $
#82
0"
#83
03
01
12
10
1.
0/
1-
1+
0,
1*
1(
b1010000 !
b1010000 %
0)
1"
b1010000 $
#84
0"
#85
0*
0(
b1010010 !
b1010010 %
1)
1"
b1010010 $
#86
0"
#87
0-
0+
1,
1*
1(
b1010100 !
b1010100 %
0)
1"
b1010100 $
#88
0"
#89
0*
0(
b1010110 !
b1010110 %
1)
1"
b1010110 $
#90
0"
#91
00
0.
1/
1-
1+
0,
1*
1(
b1011000 !
b1011000 %
0)
1"
b1011000 $
#92
0"
#93
0*
0(
b1011010 !
b1011010 %
1)
1"
b1011010 $
#94
0"
#95
0-
0+
1,
1*
1(
b1011100 !
b1011100 %
0)
1"
b1011100 $
#96
0"
#97
0*
0(
b1011110 !
b1011110 %
1)
1"
b1011110 $
#98
0"
#99
06
04
15
13
11
02
10
1.
0/
1-
1+
0,
1*
1(
b1100000 !
b1100000 %
0)
1"
b1100000 $
#100
0"
#101
0*
0(
b1100010 !
b1100010 %
1)
1"
b1100010 $
#102
0"
#103
0-
0+
1,
1*
1(
b1100100 !
b1100100 %
0)
1"
b1100100 $
#104
0"
#105
0*
0(
b1100110 !
b1100110 %
1)
1"
b1100110 $
#106
0"
#107
00
0.
1/
1-
1+
0,
1*
1(
b1101000 !
b1101000 %
0)
1"
b1101000 $
#108
0"
#109
0*
0(
b1101010 !
b1101010 %
1)
1"
b1101010 $
#110
0"
#111
0-
0+
1,
1*
1(
b1101100 !
b1101100 %
0)
1"
b1101100 $
#112
0"
#113
0*
0(
b1101110 !
b1101110 %
1)
1"
b1101110 $
#114
0"
#115
03
01
12
10
1.
0/
1-
1+
0,
1*
1(
b1110000 !
b1110000 %
0)
1"
b1110000 $
#116
0"
#117
0*
0(
b1110010 !
b1110010 %
1)
1"
b1110010 $
#118
0"
#119
0-
0+
1,
1*
1(
b1110100 !
b1110100 %
0)
1"
b1110100 $
#120
0"
#121
0*
0(
b1110110 !
b1110110 %
1)
1"
b1110110 $
#122
0"
#123
00
0.
1/
1-
1+
0,
1*
1(
b1111000 !
b1111000 %
0)
1"
b1111000 $
#124
0"
#125
0*
0(
b1111010 !
b1111010 %
1)
1"
b1111010 $
#126
0"
#127
0-
0+
1,
1*
1(
b1111100 !
b1111100 %
0)
1"
b1111100 $
#128
0"
#129
0*
0(
b1111110 !
b1111110 %
1)
1"
b1111110 $
#130
0"
#131
0:
1;
19
17
08
16
14
05
13
11
02
10
1.
0/
1-
1+
0,
1*
1(
b10000000 !
b10000000 %
0)
1"
b10000000 $
#132
0"
#133
0*
0(
b10000010 !
b10000010 %
1)
1"
b10000010 $
#134
0"
#135
0-
0+
1,
1*
1(
b10000100 !
b10000100 %
0)
1"
b10000100 $
#136
0"
#137
0*
0(
b10000110 !
b10000110 %
1)
1"
b10000110 $
#138
0"
#139
00
0.
1/
1-
1+
0,
1*
1(
b10001000 !
b10001000 %
0)
1"
b10001000 $
#140
0"
#141
0*
0(
b10001010 !
b10001010 %
1)
1"
b10001010 $
#142
0"
#143
0-
0+
1,
1*
1(
b10001100 !
b10001100 %
0)
1"
b10001100 $
#144
0"
#145
0*
0(
b10001110 !
b10001110 %
1)
1"
b10001110 $
#146
0"
#147
03
01
12
10
1.
0/
1-
1+
0,
1*
1(
b10010000 !
b10010000 %
0)
1"
b10010000 $
#148
0"
#149
0*
0(
b10010010 !
b10010010 %
1)
1"
b10010010 $
#150
0"
#151
0-
0+
1,
1*
1(
b10010100 !
b10010100 %
0)
1"
b10010100 $
#152
0"
#153
0*
0(
b10010110 !
b10010110 %
1)
1"
b10010110 $
#154
0"
#155
00
0.
1/
1-
1+
0,
1*
1(
b10011000 !
b10011000 %
0)
1"
b10011000 $
#156
0"
#157
0*
0(
b10011010 !
b10011010 %
1)
1"
b10011010 $
#158
0"
#159
0-
0+
1,
1*
1(
b10011100 !
b10011100 %
0)
1"
b10011100 $
#160
0"
#161
0*
0(
b10011110 !
b10011110 %
1)
1"
b10011110 $
#162
0"
#163
06
04
15
13
11
02
10
1.
0/
1-
1+
0,
1*
1(
b10100000 !
b10100000 %
0)
1"
b10100000 $
#164
0"
#165
0*
0(
b10100010 !
b10100010 %
1)
1"
b10100010 $
#166
0"
#167
0-
0+
1,
1*
1(
b10100100 !
b10100100 %
0)
1"
b10100100 $
#168
0"
#169
0*
0(
b10100110 !
b10100110 %
1)
1"
b10100110 $
#170
0"
#171
00
0.
1/
1-
1+
0,
1*
1(
b10101000 !
b10101000 %
0)
1"
b10101000 $
#172
0"
#173
0*
0(
b10101010 !
b10101010 %
1)
1"
b10101010 $
#174
0"
#175
0-
0+
1,
1*
1(
b10101100 !
b10101100 %
0)
1"
b10101100 $
#176
0"
#177
0*
0(
b10101110 !
b10101110 %
1)
1"
b10101110 $
#178
0"
#179
03
01
12
10
1.
0/
1-
1+
0,
1*
1(
b10110000 !
b10110000 %
0)
1"
b10110000 $
#180
0"
#181
0*
0(
b10110010 !
b10110010 %
1)
1"
b10110010 $
#182
0"
#183
0-
0+
1,
1*
1(
b10110100 !
b10110100 %
0)
1"
b10110100 $
#184
0"
#185
0*
0(
b10110110 !
b10110110 %
1)
1"
b10110110 $
#186
0"
#187
00
0.
1/
1-
1+
0,
1*
1(
b10111000 !
b10111000 %
0)
1"
b10111000 $
#188
0"
#189
0*
0(
b10111010 !
b10111010 %
1)
1"
b10111010 $
#190
0"
#191
0-
0+
1,
1*
1(
b10111100 !
b10111100 %
0)
1"
b10111100 $
#192
0"
#193
0*
0(
b10111110 !
b10111110 %
1)
1"
b10111110 $
#194
0"
#195
09
07
18
16
14
05
13
11
02
10
1.
0/
1-
1+
0,
1*
1(
b11000000 !
b11000000 %
0)
1"
b11000000 $
#196
0"
#197
0*
0(
b11000010 !
b11000010 %
1)
1"
b11000010 $
#198
0"
#199
0-
0+
1,
1*
1(
b11000100 !
b11000100 %
0)
1"
b11000100 $
#200
0"
#201
0*
0(
b11000110 !
b11000110 %
1)
1"
b11000110 $
#202
0"
#203
00
0.
1/
1-
1+
0,
1*
1(
b11001000 !
b11001000 %
0)
1"
b11001000 $
#204
0"
#205
0*
0(
b11001010 !
b11001010 %
1)
1"
b11001010 $
#206
0"
#207
0-
0+
1,
1*
1(
b11001100 !
b11001100 %
0)
1"
b11001100 $
#208
0"
#209
0*
0(
b11001110 !
b11001110 %
1)
1"
b11001110 $
#210
0"
#211
03
01
12
10
1.
0/
1-
1+
0,
1*
1(
b11010000 !
b11010000 %
0)
1"
b11010000 $
#212
0"
#213
0*
0(
b11010010 !
b11010010 %
1)
1"
b11010010 $
#214
0"
#215
0-
0+
1,
1*
1(
b11010100 !
b11010100 %
0)
1"
b11010100 $
#216
0"
#217
0*
0(
b11010110 !
b11010110 %
1)
1"
b11010110 $
#218
0"
#219
00
0.
1/
1-
1+
0,
1*
1(
b11011000 !
b11011000 %
0)
1"
b11011000 $
#220
0"
#221
0*
0(
b11011010 !
b11011010 %
1)
1"
b11011010 $
#222
0"
#223
0-
0+
1,
1*
1(
b11011100 !
b11011100 %
0)
1"
b11011100 $
#224
0"
#225
0*
0(
b11011110 !
b11011110 %
1)
1"
b11011110 $
#226
0"
#227
06
04
15
13
11
02
10
1.
0/
1-
1+
0,
1*
1(
b11100000 !
b11100000 %
0)
1"
b11100000 $
#228
0"
#229
0*
0(
b11100010 !
b11100010 %
1)
1"
b11100010 $
#230
0"
#231
0-
0+
1,
1*
1(
b11100100 !
b11100100 %
0)
1"
b11100100 $
#232
0"
#233
0*
0(
b11100110 !
b11100110 %
1)
1"
b11100110 $
#234
0"
#235
00
0.
1/
1-
1+
0,
1*
1(
b11101000 !
b11101000 %
0)
1"
b11101000 $
#236
0"
#237
0*
0(
b11101010 !
b11101010 %
1)
1"
b11101010 $
#238
0"
#239
0-
0+
1,
1*
1(
b11101100 !
b11101100 %
0)
1"
b11101100 $
#240
0"
#241
0*
0(
b11101110 !
b11101110 %
1)
1"
b11101110 $
#242
0"
#243
03
01
12
10
1.
0/
1-
1+
0,
1*
1(
b11110000 !
b11110000 %
0)
1"
b11110000 $
#244
0"
#245
0*
0(
b11110010 !
b11110010 %
1)
1"
b11110010 $
#246
0"
#247
0-
0+
1,
1*
1(
b11110100 !
b11110100 %
0)
1"
b11110100 $
#248
0"
#249
0*
0(
b11110110 !
b11110110 %
1)
1"
b11110110 $
#250
0"
#251
00
0.
1/
1-
1+
0,
1*
1(
b11111000 !
b11111000 %
0)
1"
b11111000 $
#252
0"
#253
0*
0(
b11111010 !
b11111010 %
1)
1"
b11111010 $
#254
0"
#255
0-
0+
1,
1*
1(
b11111100 !
b11111100 %
0)
1"
b11111100 $
#256
0"
#257
0*
0(
b11111110 !
b11111110 %
1)
1"
b11111110 $
#258
0"
#259
1:
0;
19
17
08
16
14
05
13
11
02
10
1.
0/
1-
1+
0,
1*
1(
b0 !
b0 %
0)
1"
b0 $
#260
0"
#261
0*
0(
b10 !
b10 %
1)
1"
